topsis_HimanshuBhumbla_102203043/__init__.py
topsis_HimanshuBhumbla_102203043/main.py
topsis_HimanshuBhumbla_102203043-0.2.0.dist-info/METADATA
topsis_HimanshuBhumbla_102203043-0.2.0.dist-info/WHEEL
topsis_HimanshuBhumbla_102203043-0.2.0.dist-info/entry_points.txt
topsis_HimanshuBhumbla_102203043-0.2.0.dist-info/top_level.txt
topsis_HimanshuBhumbla_102203043-0.2.0.dist-info/RECORD
