Metadata-Version: 2.2
Name: topsis-HimanshuBhumbla-102203043
Version: 0.2.0
Summary: A Python package to perform Topsis analysis.
Home-page: https://github.com/BHimanshu3114/Topsis
Author: Himanshu Bhumbla
Classifier: Programming Language :: Python :: 3
Classifier: Operating System :: OS Independent
Requires-Python: >=3.6
Requires-Dist: pandas
Requires-Dist: numpy
Dynamic: author
Dynamic: classifier
Dynamic: description
Dynamic: description-content-type
Dynamic: home-page
Dynamic: requires-dist
Dynamic: requires-python
Dynamic: summary
